example/__init__.py
example/app.py
example/events.py
example/styles.py
example/simple_app/__init__.py
example/simple_app/app.py
example/simple_app/events.py
example/simple_app/styles.py
toga_layout/__init__.py
toga_layout/layout.py
toga_layout/utils.py
toga_layout_builder-0.3.0.dist-info/METADATA
toga_layout_builder-0.3.0.dist-info/WHEEL
toga_layout_builder-0.3.0.dist-info/top_level.txt
toga_layout_builder-0.3.0.dist-info/RECORD
