Metadata-Version: 2.1
Name: toga-layout-builder
Version: 0.3.0
Summary: Toga Layout
Home-page: https://github.com/ignaciocabeza/toga-layout-builder
Author: Ignacio Cabeza
Author-email: ignaciocabeza@gmail.com
License: UNKNOWN
Platform: UNKNOWN
Classifier: Programming Language :: Python :: 3
Classifier: License :: OSI Approved :: MIT License
Classifier: Operating System :: OS Independent
Requires-Python: >=3.7
Requires-Dist: toga
Requires-Dist: pyyaml
